macos_tags/__init__.py
macos_tags/_api.py
macos_tags/py.typed
macos_tags-1.5.0.dist-info/LICENSE
macos_tags-1.5.0.dist-info/WHEEL
macos_tags-1.5.0.dist-info/METADATA
macos_tags-1.5.0.dist-info/RECORD
