Metadata-Version: 2.1
Name: macos-tags
Version: 1.5.0
Summary: Use tags to organize files on Mac from Python
Home-page: https://macos-tags.dmkskn.com
License: MIT
Keywords: macos,tags
Author: Dima Koskin
Author-email: dmksknn@gmail.com
Requires-Python: >=3.6,<4.0
Classifier: License :: OSI Approved :: MIT License
Classifier: Operating System :: MacOS
Classifier: Programming Language :: Python :: 3
Classifier: Programming Language :: Python :: 3 :: Only
Classifier: Programming Language :: Python :: 3.6
Classifier: Programming Language :: Python :: 3.7
Classifier: Programming Language :: Python :: 3.8
Classifier: Topic :: Software Development :: Libraries :: Python Modules
Requires-Dist: mdfind-wrapper (>=0.1.3,<0.2.0)
Requires-Dist: xattr (>=0.9.7,<0.10.0)
Project-URL: Repository, https://github.com/dmkskn/macos-tags
